<?xml version="1.0" encoding="UTF-8"?>
<!DOCTYPE mapper PUBLIC "-//mybatis.org//DTD Mapper 3.0//EN" "http://mybatis.org/dtd/mybatis-3-mapper.dtd">
<mapper namespace="biubiu.Dao.Job_seekerMapper">
  <resultMap id="BaseResultMap" type="biubiu.Model.Job_seeker">
    <!--
      WARNING - @mbggenerated
      This element is automatically generated by MyBatis Generator, do not modify.
    -->
    <id column="id" jdbcType="INTEGER" property="id" />
    <result column="name" jdbcType="VARCHAR" property="name" />
    <result column="phone" jdbcType="VARCHAR" property="phone" />
    <result column="job_purpose" jdbcType="INTEGER" property="jobPurpose" />
  </resultMap>
  <sql id="Base_Column_List">
    <!--
      WARNING - @mbggenerated
      This element is automatically generated by MyBatis Generator, do not modify.
    -->
    id, name, phone, job_purpose
  </sql>
  <select id="selectByPrimaryKey" parameterType="java.lang.Integer" resultMap="BaseResultMap">
    <!--
      WARNING - @mbggenerated
      This element is automatically generated by MyBatis Generator, do not modify.
    -->
    select 
    <include refid="Base_Column_List" />
    from job_seeker
    where id = #{id,jdbcType=INTEGER}
  </select>
  <delete id="deleteByPrimaryKey" parameterType="java.lang.Integer">
    <!--
      WARNING - @mbggenerated
      This element is automatically generated by MyBatis Generator, do not modify.
    -->
    delete from job_seeker
    where id = #{id,jdbcType=INTEGER}
  </delete>
  <insert id="insert" parameterType="biubiu.Model.Job_seeker">
    <!--
      WARNING - @mbggenerated
      This element is automatically generated by MyBatis Generator, do not modify.
    -->
    insert into job_seeker (id, name, phone, 
      job_purpose)
    values (#{id,jdbcType=INTEGER}, #{name,jdbcType=VARCHAR}, #{phone,jdbcType=VARCHAR}, 
      #{jobPurpose,jdbcType=INTEGER})
  </insert>
  <insert id="insertSelective" parameterType="biubiu.Model.Job_seeker">
    <!--
      WARNING - @mbggenerated
      This element is automatically generated by MyBatis Generator, do not modify.
    -->
    insert into job_seeker
    <trim prefix="(" suffix=")" suffixOverrides=",">
      <if test="id != null">
        id,
      </if>
      <if test="name != null">
        name,
      </if>
      <if test="phone != null">
        phone,
      </if>
      <if test="jobPurpose != null">
        job_purpose,
      </if>
    </trim>
    <trim prefix="values (" suffix=")" suffixOverrides=",">
      <if test="id != null">
        #{id,jdbcType=INTEGER},
      </if>
      <if test="name != null">
        #{name,jdbcType=VARCHAR},
      </if>
      <if test="phone != null">
        #{phone,jdbcType=VARCHAR},
      </if>
      <if test="jobPurpose != null">
        #{jobPurpose,jdbcType=INTEGER},
      </if>
    </trim>
  </insert>
  <update id="updateByPrimaryKeySelective" parameterType="biubiu.Model.Job_seeker">
    <!--
      WARNING - @mbggenerated
      This element is automatically generated by MyBatis Generator, do not modify.
    -->
    update job_seeker
    <set>
      <if test="name != null">
        name = #{name,jdbcType=VARCHAR},
      </if>
      <if test="phone != null">
        phone = #{phone,jdbcType=VARCHAR},
      </if>
      <if test="jobPurpose != null">
        job_purpose = #{jobPurpose,jdbcType=INTEGER},
      </if>
    </set>
    where id = #{id,jdbcType=INTEGER}
  </update>
  <update id="updateByPrimaryKey" parameterType="biubiu.Model.Job_seeker">
    <!--
      WARNING - @mbggenerated
      This element is automatically generated by MyBatis Generator, do not modify.
    -->
    update job_seeker
    set name = #{name,jdbcType=VARCHAR},
      phone = #{phone,jdbcType=VARCHAR},
      job_purpose = #{jobPurpose,jdbcType=INTEGER}
    where id = #{id,jdbcType=INTEGER}
  </update>
  <select id="selectAll" resultMap="BaseResultMap">
    select * from job_seeker
  </select>
</mapper>